{
    "data": {
        "type": "MARKET",
        "brand": "lumo",
        "planId": "LU2444883MS@VEC",
        "fuelType": "GAS",
        "brandName": "Lumo Energy",
        "geography": {
            "distributors": [
                "AusNet Services (gas)"
            ],
            "includedPostcodes": [
                "3024",
                "3029",
                "3030",
                "3211",
                "3214",
                "3215",
                "3216",
                "3217",
                "3218",
                "3219",
                "3220",
                "3221",
                "3222",
                "3223",
                "3224",
                "3225",
                "3226",
                "3227",
                "3228",
                "3337",
                "3338",
                "3355",
                "3427",
                "3429"
            ]
        },
        "displayName": "Lumo Basic",
        "effectiveTo": "2023-03-14T13:00:00Z",
        "gasContract": {
            "terms": "For full terms and conditions applicable to this offer, please visit https://www.lumoenergy.com.au/terms.",
            "isFixed": false,
            "variation": "We may vary your rates in line with our Terms and Conditions and in accordance with the Regulatory Requirements. We will give you written notice of at least 5 business days prior to the variation.",
            "incentives": [
                {
                    "category": "OTHER",
                    "description": "Free Standard Moves",
                    "displayName": "Free Standard Moves",
                    "eligibility": "We will cover the costs for standard connections and disconnections when you move and reconnect with Lumo in Victoria. Exclusions and conditions apply. See lumoenergy.com.au/freemoves for full details."
                }
            ],
            "eligibility": [
                {
                    "type": "OTHER",
                    "information": "This offer is available to small business customers within the Ausnet Services Central 1 distribution zone and is subject to the identification of the network tariff and metering requirements."
                }
            ],
            "pricingModel": "SINGLE_RATE",
            "tariffPeriod": [
                {
                    "endDate": "05-31",
                    "startDate": "10-01",
                    "singleRate": {
                        "rates": [
                            {
                                "volume": 100,
                                "unitPrice": "2.33"
                            },
                            {
                                "volume": 100,
                                "unitPrice": "2.20"
                            },
                            {
                                "volume": 1200,
                                "unitPrice": "2.08"
                            },
                            {
                                "unitPrice": "2.06"
                            }
                        ],
                        "period": "P1D",
                        "displayName": "Off Peak"
                    },
                    "displayName": "Off Peak",
                    "rateBlockUType": "singleRate",
                    "dailySupplyCharges": "125.65"
                },
                {
                    "endDate": "09-30",
                    "startDate": "06-01",
                    "singleRate": {
                        "rates": [
                            {
                                "volume": 100,
                                "unitPrice": "2.83"
                            },
                            {
                                "volume": 100,
                                "unitPrice": "2.67"
                            },
                            {
                                "volume": 1200,
                                "unitPrice": "2.60"
                            },
                            {
                                "unitPrice": "2.50"
                            }
                        ],
                        "period": "P1D",
                        "displayName": "Peak"
                    },
                    "displayName": "Peak",
                    "rateBlockUType": "singleRate",
                    "dailySupplyCharges": "125.65"
                }
            ],
            "billFrequency": [
                "P2M"
            ],
            "paymentOption": [
                "PAPER_BILL"
            ],
            "coolingOffDays": 10,
            "onExpiryDescription": "Your contract is ongoing until it is ended by you or us. No exit fees."
        },
        "lastUpdated": "2023-03-14T23:01:32Z",
        "customerType": "BUSINESS",
        "effectiveFrom": "2023-02-20T13:00:00Z"
    },
    "meta": {},
    "links": {
        "self": "https://cdr.energymadeeasy.gov.au/lumo/cds-au/v1/energy/plans/LU2444883MS@VEC"
    }
}