{
    "data": {
        "type": "MARKET",
        "brand": "agl",
        "planId": "AGL464267MRE2@EME",
        "fuelType": "ELECTRICITY",
        "brandName": "AGL",
        "geography": {
            "distributors": [
                "Endeavour"
            ],
            "includedPostcodes": [
                "2113",
                "2114",
                "2115",
                "2116",
                "2117",
                "2118",
                "2119",
                "2120",
                "2121",
                "2122",
                "2125",
                "2126",
                "2142",
                "2145",
                "2146",
                "2147",
                "2148",
                "2150",
                "2151",
                "2152",
                "2153",
                "2154",
                "2155",
                "2156",
                "2157",
                "2158",
                "2159",
                "2160",
                "2161",
                "2162",
                "2163",
                "2164",
                "2165",
                "2166",
                "2167",
                "2168",
                "2170",
                "2171",
                "2172",
                "2173",
                "2174",
                "2175",
                "2176",
                "2177",
                "2178",
                "2179",
                "2198",
                "2200",
                "2213",
                "2214",
                "2233",
                "2250",
                "2257",
                "2283",
                "2304",
                "2323",
                "2325",
                "2328",
                "2329",
                "2330",
                "2500",
                "2502",
                "2505",
                "2506",
                "2508",
                "2515",
                "2516",
                "2517",
                "2518",
                "2519",
                "2525",
                "2526",
                "2527",
                "2528",
                "2529",
                "2530",
                "2533",
                "2534",
                "2536",
                "2537",
                "2555",
                "2556",
                "2557",
                "2558",
                "2559",
                "2560",
                "2563",
                "2564",
                "2565",
                "2566",
                "2567",
                "2568",
                "2569",
                "2570",
                "2571",
                "2572",
                "2573",
                "2574",
                "2575",
                "2576",
                "2577",
                "2578",
                "2579",
                "2580",
                "2622",
                "2745",
                "2747",
                "2748",
                "2749",
                "2750",
                "2751",
                "2752",
                "2753",
                "2754",
                "2756",
                "2757",
                "2758",
                "2759",
                "2760",
                "2761",
                "2762",
                "2763",
                "2765",
                "2766",
                "2767",
                "2768",
                "2769",
                "2770",
                "2773",
                "2774",
                "2775",
                "2776",
                "2777",
                "2778",
                "2779",
                "2780",
                "2782",
                "2783",
                "2784",
                "2785",
                "2786",
                "2787",
                "2790",
                "2795",
                "2800",
                "2845",
                "2846",
                "2847",
                "2848",
                "2849",
                "2850"
            ]
        },
        "displayName": "Residential Flexible Saver",
        "lastUpdated": "2022-08-04T01:30:45.847Z",
        "customerType": "RESIDENTIAL",
        "effectiveFrom": "2022-08-04T00:00:00.000Z",
        "electricityContract": {
            "fees": [
                {
                    "term": "FIXED",
                    "type": "CONNECTION",
                    "description": "May be charged when manually reconnecting or reading your meter when you move into a property or change retailer. Incl GST. Fees may vary."
                },
                {
                    "term": "FIXED",
                    "type": "DISCONNECT_MOVE_OUT",
                    "description": "May be charged when manually disconnecting or reading your meter when you move out of a property or change retailer. Incl GST. Fees may vary."
                },
                {
                    "term": "FIXED",
                    "type": "DISCONNECT_NON_PAY",
                    "description": "Fee may be charged when manually disconnecting your meter in other circumstances, such as non-payment. Includes GST. Fees may vary."
                },
                {
                    "term": "FIXED",
                    "type": "LATE_PAYMENT",
                    "description": "A late payment fee may be charged when full payment has not been received by the bill due date. This amount is not subject to GST"
                },
                {
                    "rate": "0.17",
                    "term": "PERCENT_OF_BILL",
                    "type": "PAYMENT_PROCESSING",
                    "description": "The amount is GST inclusive and applies to payments made by debit cards."
                },
                {
                    "rate": "0.45",
                    "term": "PERCENT_OF_BILL",
                    "type": "PAYMENT_PROCESSING",
                    "description": "The amount is GST inclusive and applies to card payments made at Australia Post outlets."
                },
                {
                    "rate": "0.66",
                    "term": "PERCENT_OF_BILL",
                    "type": "CC_PROCESSING",
                    "description": "The amount is GST inclusive and applies to payments made by credit cards."
                },
                {
                    "term": "FIXED",
                    "type": "RECONNECTION",
                    "description": "May be charged when manually reconnecting in other circumstances, such as after disconnection for non-payment. Includes GST. Fees may vary"
                },
                {
                    "term": "FIXED",
                    "type": "CONNECTION",
                    "description": "Fee may be charged when remotely reconnecting your meter when you move into a property or change retailer. Includes GST. Fees may vary."
                },
                {
                    "term": "FIXED",
                    "type": "DISCONNECT_MOVE_OUT",
                    "description": "Fee may be charged when remotely disconnecting your meter when you move out of a property or change retailer. Includes GST. Fees may vary."
                }
            ],
            "terms": "This offer applies to customers with an applicable network tariff. For solar feed-in tariff eligibility, or for further information about the terms and conditions applicable to this energy offer, please contact AGL on 131 245 or visit agl.com.au",
            "isFixed": false,
            "timeZone": "LOCAL",
            "variation": "This plan also includes variable rates, retail fees and charges, which can change at any time with notice to you. If we vary your rates, we will give you at least 5 business days prior notice of the variation. Other charges may be varied with notice to you.",
            "meterTypes": [
                "Type 4",
                "Type 4a",
                "Type 5",
                "Type 6"
            ],
            "eligibility": [
                {
                    "type": "OTHER",
                    "description": "Offer only available by signing up with an authorised AGL representative.",
                    "information": "Authorised AGL representative"
                }
            ],
            "pricingModel": "SINGLE_RATE",
            "tariffPeriod": [
                {
                    "endDate": "06-30",
                    "startDate": "07-01",
                    "singleRate": {
                        "rates": [
                            {
                                "volume": 4900,
                                "unitPrice": "26.24"
                            },
                            {
                                "volume": null,
                                "unitPrice": "26.24"
                            }
                        ],
                        "period": "P1Y",
                        "description": "Peak",
                        "displayName": "Domestic All Time Peak"
                    },
                    "displayName": "Single Rate Tariff Period",
                    "rateBlockUType": "singleRate",
                    "dailySupplyCharges": "95.74"
                }
            ],
            "billFrequency": [
                "P3M",
                "P1M"
            ],
            "paymentOption": [
                "PAPER_BILL",
                "DIRECT_DEBIT",
                "CREDIT_CARD",
                "BPAY"
            ],
            "coolingOffDays": "10",
            "greenPowerCharges": [
                {
                    "type": "FIXED_PER_WEEK",
                    "tiers": [
                        {
                            "amount": "1.000000",
                            "percentGreen": "20"
                        }
                    ],
                    "scheme": "GREENPOWER",
                    "description": "For $1 per week inc. GST we ensure energy equal to 20% of your usage will be fed into the grid from Accredited GreenPower generators."
                },
                {
                    "type": "FIXED_PER_UNIT",
                    "tiers": [
                        {
                            "amount": "0.044000",
                            "percentGreen": "100"
                        }
                    ],
                    "scheme": "GREENPOWER",
                    "description": "For 4.4c /kWh inc. GST we ensure energy equal to 100% of your usage will be fed into the grid from Accredited GreenPower generators."
                }
            ],
            "solarFeedInTariff": [
                {
                    "scheme": "OTHER",
                    "payerType": "RETAILER",
                    "description": "AGL Retailer Feed-in Tariff (exc GST if any)",
                    "displayName": "Single Rate Solar FiT",
                    "tariffUType": "singleTariff",
                    "singleTariff": {
                        "amount": "5.000000"
                    }
                }
            ],
            "onExpiryDescription": "Your market contract is ongoing. From time to time, AGL reviews its offers and this offer will be reviewed with consideration to AGL generally available market offers"
        }
    },
    "meta": {},
    "links": {
        "self": "https://cdr.energymadeeasy.gov.au/agl/cds-au/v1/energy/plans/AGL464267MRE2@EME"
    }
}