{
    "data": {
        "type": "MARKET",
        "brand": "red-energy",
        "planId": "RED456199MR@VEC",
        "fuelType": "GAS",
        "brandName": "Red Energy",
        "geography": {
            "distributors": [
                "Australian Gas Networks"
            ],
            "includedPostcodes": [
                "3561",
                "3564",
                "3616",
                "3618",
                "3620",
                "3621",
                "3622",
                "3623",
                "3624",
                "3629",
                "3630",
                "3631",
                "3658",
                "3659",
                "3660",
                "3662",
                "3663",
                "3664",
                "3665",
                "3666",
                "3669",
                "3672",
                "3677",
                "3678",
                "3688",
                "3690",
                "3691",
                "3694",
                "3753",
                "3756",
                "3757",
                "3758",
                "3763",
                "3764",
                "3775"
            ]
        },
        "displayName": "Qantas Red Saver (Bundled)",
        "gasContract": {
            "terms": "For full terms and conditions applicable to this offer, please visit https://www.redenergy.com.au/terms",
            "isFixed": false,
            "variation": "We may vary your rates in line with our Terms and Conditions and in accordance with the Relevant Laws. We will give you written notice of at least 5 business days prior to the variation.",
            "incentives": [
                {
                    "category": "OTHER",
                    "description": "Qantas Points",
                    "displayName": "Qantas Points",
                    "eligibility": "Get 5,000 bonus Qantas Points when Red Energy becomes responsible for the supply of your electricity and 3 Qantas Points per $1 on every gas bill, when you pay on time. For T&Cs see redenergy.com.au/terms"
                },
                {
                    "category": "OTHER",
                    "description": "Carbon Neutral Gas",
                    "displayName": "Carbon Neutral Gas",
                    "eligibility": "Carbon Neutral Gas is certified by Climate Active and is an optional add-on charged at an additional rate of 0.242 cents per MJ inc GST and may be varied or ended by notice under relevant laws. See www.redenergy.com.au/carbon-neutral-gas "
                }
            ],
            "eligibility": [
                {
                    "type": "OTHER",
                    "information": "Only available to Qantas Red business customers who are nominated as a Director or Authorised Person on a Qantas Red business plan who are also an account holder on a Qantas Red residential premises."
                }
            ],
            "pricingModel": "SINGLE_RATE",
            "tariffPeriod": [
                {
                    "endDate": "12-31",
                    "startDate": "01-01",
                    "singleRate": {
                        "rates": [
                            {
                                "volume": 27,
                                "unitPrice": "3.44"
                            },
                            {
                                "volume": 21,
                                "unitPrice": "3.07"
                            },
                            {
                                "unitPrice": "2.427"
                            }
                        ],
                        "period": "P1D",
                        "displayName": "Peak"
                    },
                    "displayName": "Period",
                    "rateBlockUType": "singleRate",
                    "dailySupplyCharges": "75.00"
                }
            ],
            "billFrequency": [
                "P2M"
            ],
            "paymentOption": [
                "PAPER_BILL"
            ],
            "coolingOffDays": 10,
            "onExpiryDescription": "Your contract is ongoing until it is ended by you or us."
        },
        "lastUpdated": "2023-04-12T04:31:44Z",
        "customerType": "RESIDENTIAL",
        "effectiveFrom": "2023-04-18T14:00:00Z"
    },
    "meta": {},
    "links": {
        "self": "https://cdr.energymadeeasy.gov.au/red-energy/cds-au/v1/energy/plans/RED456199MR@VEC"
    }
}