{
    "data": {
        "type": "STANDING",
        "brand": "dodo",
        "planId": "DOD400406SS@VEC",
        "fuelType": "ELECTRICITY",
        "brandName": "Dodo",
        "geography": {
            "distributors": [
                "Citipower"
            ],
            "includedPostcodes": [
                "3000",
                "3002",
                "3003",
                "3004",
                "3005",
                "3006",
                "3008",
                "3010",
                "3011",
                "3031",
                "3051",
                "3052",
                "3053",
                "3054",
                "3055",
                "3056",
                "3057",
                "3065",
                "3066",
                "3067",
                "3068",
                "3070",
                "3071",
                "3078",
                "3101",
                "3102",
                "3103",
                "3104",
                "3121",
                "3122",
                "3123",
                "3124",
                "3125",
                "3126",
                "3127",
                "3129",
                "3141",
                "3142",
                "3143",
                "3144",
                "3161",
                "3181",
                "3182",
                "3183",
                "3205",
                "3206",
                "3207"
            ]
        },
        "displayName": "Business Standing - Single Rate with Controlled Load",
        "effectiveTo": "2023-06-29T14:00:00Z",
        "lastUpdated": "2023-06-30T10:10:37Z",
        "customerType": "BUSINESS",
        "effectiveFrom": "2022-06-30T14:00:00Z",
        "electricityContract": {
            "fees": [
                {
                    "term": "FIXED",
                    "type": "CONNECTION",
                    "amount": "39.00",
                    "description": "A connection fee may apply each time you request to energise a property.\nFor further details on the information presented in this fact sheet, or the terms and conditions of the contract, please visit www.dodo.com/energy/terms-prices-and-regulatory-information."
                },
                {
                    "term": "FIXED",
                    "type": "DISCONNECTION",
                    "amount": "39.00",
                    "description": "A disconnection fee may apply each time you request to de-energise a property."
                },
                {
                    "term": "FIXED",
                    "type": "DD_DISHONOUR",
                    "amount": "9.50",
                    "description": "Dishonoured Payment fee may apply to payments we attempt that are subsequently declined."
                }
            ],
            "terms": "See our Standing Offer terms and conditions at www.dodo.com/energy/terms-prices-and-regulatory-information.",
            "isFixed": false,
            "timeZone": "AEST",
            "variation": "We may vary our rates, no more than once every 6 months. We will provide notification to you, publish the variation on our website and in a newspaper at least 10 business days before it starts.",
            "eligibility": [
                {
                    "type": "OTHER",
                    "information": "Applicable to a Small Business Customer in the Citipower distribution zone & verification of meter type. See terms & conditions for other eligibility criteria, including solar feed-in tariff eligibility."
                }
            ],
            "pricingModel": "SINGLE_RATE_CONT_LOAD",
            "tariffPeriod": [
                {
                    "endDate": "12-31",
                    "startDate": "01-01",
                    "singleRate": {
                        "rates": [
                            {
                                "unitPrice": "19.6909"
                            }
                        ],
                        "period": "P1D",
                        "description": "for the personal use of the residents of the premises, all day, everyday",
                        "displayName": "Anytime"
                    },
                    "displayName": "Period",
                    "rateBlockUType": "singleRate",
                    "dailySupplyCharges": "126.00"
                }
            ],
            "billFrequency": [
                "P3M"
            ],
            "paymentOption": [
                "PAPER_BILL"
            ],
            "controlledLoad": [
                {
                    "singleRate": {
                        "rates": [
                            {
                                "unitPrice": "14.0181"
                            }
                        ],
                        "description": "for hot water and/or storage space heaters (on for a controlled period)",
                        "displayName": "Controlled Load"
                    },
                    "displayName": "Controlled Load",
                    "rateBlockUType": "singleRate"
                }
            ],
            "coolingOffDays": 10,
            "solarFeedInTariff": [
                {
                    "scheme": "OTHER",
                    "payerType": "RETAILER",
                    "description": "General Feed in Tariff (GFIT)",
                    "displayName": "Current FIT policy",
                    "tariffUType": "singleTariff",
                    "singleTariff": {
                        "amount": "5.20"
                    }
                },
                {
                    "scheme": "PREMIUM",
                    "payerType": "RETAILER",
                    "description": "Premium Feed in Tariff (PFIT)",
                    "displayName": "Premium FIT [closed]",
                    "tariffUType": "singleTariff",
                    "singleTariff": {
                        "amount": "60.00"
                    }
                }
            ],
            "onExpiryDescription": "No Term contracts do not expire"
        }
    },
    "meta": {},
    "links": {
        "self": "https://cdr.energymadeeasy.gov.au/dodo/cds-au/v1/energy/plans/DOD400406SS@VEC"
    }
}