{
    "data": {
        "type": "STANDING",
        "brand": "momentum",
        "planId": "MOM364144SS@VEC",
        "fuelType": "GAS",
        "brandName": "Momentum Energy",
        "geography": {
            "distributors": [
                "Multinet"
            ],
            "includedPostcodes": [
                "3139",
                "3775",
                "3797",
                "3799"
            ]
        },
        "displayName": "Standing Offer Gas Multinet Yarra Valley",
        "effectiveTo": "2022-10-27T13:00:00Z",
        "gasContract": {
            "fees": [
                {
                    "term": "FIXED",
                    "type": "OTHER",
                    "amount": "7.72",
                    "description": "Move-In/Move Out Meter Read fee\nFor information on additional fees, a full schedule of charges is available from www.momentumenergy.com.au/fees"
                }
            ],
            "terms": "Full terms and conditions can be obtained from www.momentumenergy.com.au/terms or by contacting our Customer Care Team on 1800 SWITCH.",
            "isFixed": false,
            "variation": "We will give you written notice of any variations to your rates & charges under your terms and conditions in accordance with applicable legal requirements.",
            "eligibility": [
                {
                    "type": "OTHER",
                    "information": "Available to business customers with a Supply Address in Victoria in the Multinet Yarra Valley distribution area as determined by Momentum Energy using less than 1000 GJ p.a. of gas. To verify your distribution area please call us on 1800 SWITCH."
                }
            ],
            "pricingModel": "SINGLE_RATE",
            "tariffPeriod": [
                {
                    "endDate": "04-30",
                    "startDate": "11-01",
                    "singleRate": {
                        "rates": [
                            {
                                "volume": 250,
                                "unitPrice": "2.497"
                            },
                            {
                                "volume": 750,
                                "unitPrice": "2.406"
                            },
                            {
                                "volume": 500,
                                "unitPrice": "2.335"
                            },
                            {
                                "volume": 3500,
                                "unitPrice": "2.294"
                            },
                            {
                                "unitPrice": "2.249"
                            }
                        ],
                        "displayName": "Off-Peak"
                    },
                    "displayName": "Off-Peak",
                    "rateBlockUType": "singleRate",
                    "dailySupplyCharges": "109.33"
                },
                {
                    "endDate": "10-31",
                    "startDate": "05-01",
                    "singleRate": {
                        "rates": [
                            {
                                "volume": 250,
                                "unitPrice": "2.897"
                            },
                            {
                                "volume": 750,
                                "unitPrice": "2.766"
                            },
                            {
                                "volume": 500,
                                "unitPrice": "2.678"
                            },
                            {
                                "volume": 3500,
                                "unitPrice": "2.616"
                            },
                            {
                                "unitPrice": "2.568"
                            }
                        ],
                        "displayName": "Peak"
                    },
                    "displayName": "Peak",
                    "rateBlockUType": "singleRate",
                    "dailySupplyCharges": "109.33"
                }
            ],
            "billFrequency": [
                "P2M"
            ],
            "paymentOption": [
                "PAPER_BILL"
            ],
            "coolingOffDays": 10,
            "onExpiryDescription": "The agreement continues until terminated by your or us in accordance with your terms and conditions."
        },
        "lastUpdated": "2022-10-27T22:28:02Z",
        "customerType": "BUSINESS",
        "effectiveFrom": "2021-12-31T13:00:00Z"
    },
    "meta": {},
    "links": {
        "self": "https://cdr.energymadeeasy.gov.au/momentum/cds-au/v1/energy/plans/MOM364144SS@VEC"
    }
}