{
    "data": {
        "type": "STANDING",
        "brand": "1st-energy",
        "planId": "1ST405563SS@VEC",
        "fuelType": "ELECTRICITY",
        "brandName": "1st Energy",
        "geography": {
            "distributors": [
                "Jemena"
            ],
            "includedPostcodes": [
                "3011",
                "3012",
                "3013",
                "3015",
                "3016",
                "3019",
                "3020",
                "3023",
                "3025",
                "3031",
                "3032",
                "3033",
                "3034",
                "3036",
                "3037",
                "3038",
                "3039",
                "3040",
                "3041",
                "3042",
                "3043",
                "3044",
                "3045",
                "3046",
                "3047",
                "3048",
                "3049",
                "3051",
                "3052",
                "3058",
                "3059",
                "3060",
                "3061",
                "3062",
                "3063",
                "3064",
                "3068",
                "3070",
                "3072",
                "3073",
                "3074",
                "3076",
                "3078",
                "3079",
                "3081",
                "3083",
                "3084",
                "3085",
                "3086",
                "3087",
                "3335",
                "3336",
                "3337",
                "3340",
                "3427",
                "3428",
                "3429",
                "3430",
                "3431",
                "3437",
                "3750",
                "3753"
            ]
        },
        "displayName": "Victorian Default Offer, Business Single Rate",
        "lastUpdated": "2022-06-30T15:02:14Z",
        "customerType": "BUSINESS",
        "effectiveFrom": "2022-06-30T14:00:00Z",
        "electricityContract": {
            "fees": [
                {
                    "term": "FIXED",
                    "type": "CHEQUE_DISHONOUR",
                    "amount": "15.00",
                    "description": "Cheque dishonour fee\nAdditional fees may apply. For more information, please call 1300 426 594."
                },
                {
                    "term": "FIXED",
                    "type": "DD_DISHONOUR",
                    "amount": "7.50",
                    "description": "Direct debit dishonour fee"
                }
            ],
            "terms": "For further details on the information presented in this fact sheet, or the terms and conditions of the offer, please visit www.1stenergy.com.au or call 1st Energy on 1300 426 594.",
            "isFixed": false,
            "timeZone": "AEST",
            "variation": "Prices may be varied in line with your terms and conditions. If your charges are increasing we will notify you at least 5 business days prior to the variation applying.",
            "eligibility": [
                {
                    "type": "OTHER",
                    "information": "This offer is available to customers within the Jemena distribution zone with the applicable network tariff and meter configuration."
                }
            ],
            "pricingModel": "SINGLE_RATE",
            "tariffPeriod": [
                {
                    "endDate": "12-31",
                    "startDate": "01-01",
                    "singleRate": {
                        "rates": [
                            {
                                "unitPrice": "22.436"
                            }
                        ],
                        "description": "Anytime",
                        "displayName": "Anytime"
                    },
                    "displayName": "Period",
                    "rateBlockUType": "singleRate",
                    "dailySupplyCharges": "118.972"
                }
            ],
            "billFrequency": [
                "P1M"
            ],
            "paymentOption": [
                "PAPER_BILL"
            ],
            "coolingOffDays": 10,
            "solarFeedInTariff": [
                {
                    "scheme": "OTHER",
                    "payerType": "RETAILER",
                    "description": "Solar feed-in",
                    "displayName": "Current FIT policy",
                    "tariffUType": "singleTariff",
                    "singleTariff": {
                        "amount": "5.20"
                    }
                },
                {
                    "scheme": "PREMIUM",
                    "payerType": "RETAILER",
                    "description": "Premium feed-in tariff (if eligible)",
                    "displayName": "Premium FIT [closed]",
                    "tariffUType": "singleTariff",
                    "singleTariff": {
                        "amount": "60.00"
                    }
                }
            ],
            "onExpiryDescription": "Your contract continues until terminated by you or us in accordance with our terms and conditions."
        }
    },
    "meta": {},
    "links": {
        "self": "https://cdr.energymadeeasy.gov.au/1st-energy/cds-au/v1/energy/plans/1ST405563SS@VEC"
    }
}